[
    {
        "id": 1,
        "name": "harish",
        "password": 12345,
        "age": 24,
        "phone number": "9738724718",
        "order history": {
            "04-28-2022": [
                "fried Rice"
            ]
        }
    },
    {
        "id": 2,
        "name": "Venkatesh",
        "password": 973872,
        "age": 25,
        "phone number": "8892558468",
        "order history": {
            "04-28-2022": [
                "Paneer Tikka"
            ]
        }
    },
    {
        "id": 3,
        "name": "Hari Krishna",
        "password": 701921,
        "age": 27,
        "phone number": "7899154365",
        "order history": {}
    },
    {
        "id": 4,
        "name": "Sai Kumar",
        "password": 560033,
        "age": 23,
        "phone number": "8618825981",
        "order history": {}
    }
]